MANIFEST.in
README.md
setup.py
dash_annotated_syntax_highlighter/__init__.py
dash_annotated_syntax_highlighter/bundle.js
dash_annotated_syntax_highlighter/metadata.json
dash_annotated_syntax_highlighter/version.py
dash_annotated_syntax_highlighter.egg-info/PKG-INFO
dash_annotated_syntax_highlighter.egg-info/SOURCES.txt
dash_annotated_syntax_highlighter.egg-info/dependency_links.txt
dash_annotated_syntax_highlighter.egg-info/top_level.txt