Metadata-Version: 1.0
Name: dash-annotated-syntax-highlighter
Version: 0.0.1
Summary: A specialized syntax highlighter that places code comments into the margins
Home-page: UNKNOWN
Author: chriddyp
Author-email: UNKNOWN
License: MIT
Platform: UNKNOWN
